{"version":1,"resource":"file:///home/s21/C_sharp_Day01-1/src/d_01/Storage.cs","entries":[{"id":"sGlp.cs","timestamp":1706708110278},{"id":"Qknl.cs","timestamp":1706708547663},{"id":"rSP4.cs","timestamp":1706709007519},{"id":"R4mr.cs","timestamp":1706709291849},{"id":"ck7S.cs","timestamp":1706711349103},{"id":"ooHd.cs","timestamp":1706712766945},{"id":"vqLy.cs","timestamp":1706779820483},{"id":"mtLU.cs","timestamp":1706796904919},{"id":"tK5H.cs","timestamp":1706798161243},{"id":"NfAQ.cs","timestamp":1706798351081}]}